{
  "broadcastStartTime": "2026-01-25T22:00:00.000Z",
  "programSchedule": [
    {
      "videoId": "Dblx8yWI3TA",
      "title": "\"Пророцтво і очікування обіцяного Царя\" (Іс. 7:14, Міх. 5:1, Іс. 9:1-6).Віталій Зінченко, 30.11.2025",
      "startTime": 0,
      "duration": 1553
    },
    {
      "videoId": "R7z-tPPHNIY",
      "title": "Різдвяна вистава \"Червоні черевички на Різдво\", 24.12.2024",
      "startTime": 1553,
      "duration": 1929
    },
    {
      "videoId": "mrFK5i4J8tY",
      "title": "\"Молились женщины\"",
      "startTime": 3482,
      "duration": 301
    },
    {
      "videoId": "fgEK6sIGuRs",
      "title": "Храните себя от идолов (1Ин 5:21). Проповедует Парфило Андрей 21 августа 2022 года",
      "startTime": 3783,
      "duration": 1496
    },
    {
      "videoId": "Pdwtn-aneB4",
      "title": "\"Хваліть Господа!\" (Псалом 148). Микола Марйоха, 24 вересня 2023 року",
      "startTime": 5279,
      "duration": 1945
    },
    {
      "videoId": "hr0HSG10N0w",
      "title": "Вечірнє Богослужіння 06.08.2025. Свято Преображення.",
      "startTime": 7224,
      "duration": 4305
    },
    {
      "videoId": "A7y82iRvOiM",
      "title": "\"Вірим ми\". Хор церкви ЄХБ \"Дім Євангелія\"",
      "startTime": 11529,
      "duration": 265
    },
    {
      "videoId": "Au8Xgf_y6Jk",
      "title": "\"Як будувати плани на майбутнє\" (Як. 4:13-17). Віталій Зінченко, 22.09.2024",
      "startTime": 11794,
      "duration": 1128
    },
    {
      "videoId": "T_Ais26JqcE",
      "title": "Прославлення Господа 2 листопада 2025 року",
      "startTime": 12922,
      "duration": 2135
    },
    {
      "videoId": "JJ2oI0AmkPk",
      "title": "\"Благодатное и подзаконное состояние\" (Осия 10:12).  Александр Кирсанов (г.Мариупооь), 10.11.2024",
      "startTime": 15057,
      "duration": 2118
    },
    {
      "videoId": "qbk4W7jtd48",
      "title": "\"Величайшие привилегии христианина\" (2Кор 2:14-17). Андрей Парфило, 08.10.2023",
      "startTime": 17175,
      "duration": 1891
    },
    {
      "videoId": "rxh3HgEgbn8",
      "title": "Фундамент віри і цінностей у вихованні дітей. День 4. 05.06.2025",
      "startTime": 19066,
      "duration": 6896
    },
    {
      "videoId": "_y3FOHRc7mY",
      "title": "\"Наша реакция на Божьи откровения\" (Быт 28:10-22). Виталий Зинченко 13 ноября 2022 года",
      "startTime": 25962,
      "duration": 1901
    },
    {
      "videoId": "eIWrzVaB4pg",
      "title": "\"Какая польза от страданий?\" (1Пет 4:1,12; 1 Пет 5:10). Сергей Комисар, 23.06.2024",
      "startTime": 27863,
      "duration": 2573
    },
    {
      "videoId": "HmsOsrivSeo",
      "title": "\"В жизни земной всё приходит к концу\". Хоровое пение 05.11.2023",
      "startTime": 30436,
      "duration": 237
    },
    {
      "videoId": "w2LE0eTl1oQ",
      "title": "\"Христос - наша надія\" (1 Тимофія 1:1). Андрій Булигін, 27.04.2025",
      "startTime": 30673,
      "duration": 3439
    },
    {
      "videoId": "zKQ67yWdqsg",
      "title": "Пролиття крові - жертва за гріх",
      "startTime": 34112,
      "duration": 1171
    },
    {
      "videoId": "VPoZyVyb2j8",
      "title": "Прославлення Господа 31 березня 2024",
      "startTime": 35283,
      "duration": 3367
    },
    {
      "videoId": "E_t12BGJPN0",
      "title": "\"Служіння матері\" (2Тим 1:5). Микола Марйоха, 14 травня 2023 року",
      "startTime": 38650,
      "duration": 1304
    },
    {
      "videoId": "rpBs33b7J6s",
      "title": "Прославлення Господа 3 вересня 2023 року",
      "startTime": 39954,
      "duration": 1850
    },
    {
      "videoId": "GMUupxFukck",
      "title": "\"Парадокс духовного життя\" (Рим 6:1-14). Олександр Іванченко, 06.07.2025",
      "startTime": 41804,
      "duration": 1851
    },
    {
      "videoId": "UXSOhV3fsbo",
      "title": "\"Практика здорового учения для пожилых верующих\" (Тит 2:1-5). Андрей Парфило, 25.06.2023",
      "startTime": 43655,
      "duration": 2316
    },
    {
      "videoId": "GpoWD0Uemyg",
      "title": "\"Голгофа - місце Перемоги\"",
      "startTime": 45971,
      "duration": 906
    },
    {
      "videoId": "ZCGMA9D-8PE",
      "title": "Благословіння Діани Бугайової, 14.04.2024",
      "startTime": 46877,
      "duration": 1043
    },
    {
      "videoId": "0a-9C2J1asI",
      "title": "Біблійний вікенд по книзі пророка Огії. Проповідь 1. Руслан Качур, 17.06.2023",
      "startTime": 47920,
      "duration": 3277
    },
    {
      "videoId": "sMF5ZFCeik4",
      "title": "\"Життєві турботи\" (Матв. 6:25-34). Микола Марйоха, 21.12.2025",
      "startTime": 51197,
      "duration": 1367
    },
    {
      "videoId": "i-l9UuVsdsE",
      "title": "\"Свято Жнив - Історичний Екскурс\" (Вихід 23:16). Андрій Булигін 25 вересня 2022 року",
      "startTime": 52564,
      "duration": 2322
    },
    {
      "videoId": "sVtWi9mGjjM",
      "title": "\"На кого мне надеяться\"? (Пс. 145:1-10). Андрей Парфило, 21.04.2024",
      "startTime": 54886,
      "duration": 1874
    },
    {
      "videoId": "Uj5KmfW_vZM",
      "title": "\"Невірний нехай стане вірним\" (Якова 4:4-10). Віталій Зінченко, 14.07.2024",
      "startTime": 56760,
      "duration": 2432
    },
    {
      "videoId": "UMw2vdqBXLc",
      "title": "Прославлення Господа 21 травня 2023 року",
      "startTime": 59192,
      "duration": 706
    },
    {
      "videoId": "poc2Rl9Q1kc",
      "title": "\"Влада прощати\" (Матвія 9:6-8). Андрій Міщенко, 05.01.2025",
      "startTime": 59898,
      "duration": 1754
    },
    {
      "videoId": "ImmyvGKAH7M",
      "title": "\"Благодать благої вісті для язичників\" (Еф. 3:8-9). Микола Марйоха, 28.01.2024",
      "startTime": 61652,
      "duration": 1457
    },
    {
      "videoId": "Kyw6jaIeri8",
      "title": "\"Два заклики до церкви та її пастирів\" (Тит 1:1-9). Артем Бакаєв, 30.06.2024",
      "startTime": 63109,
      "duration": 1996
    },
    {
      "videoId": "IUztuRQ2b1g",
      "title": "\"Відлітають роки,мов птахи восени\". Влад та Тимофій Охріменки, 15.12.2024",
      "startTime": 65105,
      "duration": 253
    },
    {
      "videoId": "Jgb0yFVOuUE",
      "title": "\"Проклятие НЕлюбящим Христа\" (1Кор. 16:22). Андрей Парфило, 10.12.2023",
      "startTime": 65358,
      "duration": 2612
    },
    {
      "videoId": "Epp0oqjca4o",
      "title": "У Креста Христова",
      "startTime": 67970,
      "duration": 166
    },
    {
      "videoId": "WZguwzFc7vs",
      "title": "Прославлення Господа 25.12.2025",
      "startTime": 68136,
      "duration": 2062
    },
    {
      "videoId": "MiZ3sbUFNjo",
      "title": "\"Вы уже НЕ чужие и НЕ пришельцы\" (Еф 2:19). Сергей Комисар, 12 марта 2023 года",
      "startTime": 70198,
      "duration": 2223
    },
    {
      "videoId": "3VQ7_xKUgHo",
      "title": "Різдвяний дитячий хор 24.12.2024",
      "startTime": 72421,
      "duration": 2906
    },
    {
      "videoId": "V4t1i8TH2LQ",
      "title": "Прославлення Господа 01.10.2023",
      "startTime": 75327,
      "duration": 1490
    },
    {
      "videoId": "z9AQiMtXAP0",
      "title": "\"Радість в Господі\" (Лк. 2:8-11). Микола Марйоха, 25.12.2023",
      "startTime": 76817,
      "duration": 606
    },
    {
      "videoId": "uCfS6l75jM4",
      "title": "Прославлення Господа 11.01.2026",
      "startTime": 77423,
      "duration": 1526
    },
    {
      "videoId": "jbBfjikrZQs",
      "title": "Бог мой, Ты Скала моя",
      "startTime": 78949,
      "duration": 275
    },
    {
      "videoId": "8O8q4Bo5JcQ",
      "title": "\"Спокуса благополуччям нечестивих\" (Псалом 73). Андрій Міщенко 08 12 2024",
      "startTime": 79224,
      "duration": 1609
    },
    {
      "videoId": "mXgvEa1MzFU",
      "title": "Прославлення Господа 25.12.2025, ранок",
      "startTime": 80833,
      "duration": 1080
    },
    {
      "videoId": "CclgZSumQaA",
      "title": "Загальноміське Різдвяне служіння 25 грудня 2023 року",
      "startTime": 81913,
      "duration": 6740
    }
  ]
}